{
  "$schema": "https://raw.githubusercontent.com/getmanfred/mac/v0.5/schema/schema.json",
  "settings": {
    "language": "EN",
    "MACVersion": "0.5"
  },
  "aboutMe": {
    "profile": {
      "name": "Nacho",
      "surnames": "Cerrato",
      "title": ".NET Developer",
      "description": "NET Developer with experience in both national and international projects. Specialized in modern application architecture using .NET 8, Clean Architecture, and Domain-Driven Design (DDD). Passionate about building scalable, maintainable solutions with an eagerness to continuously improve and learn from my peers. Skilled in C#, .NET Core, Entity Framework, and Azure technologies. Enjoys working in Agile environments with a focus on clean code, SOLID principles, and CI/CD pipelines.",
      "avatar": {
        "link": "https://media-asgard.s3.eu-west-1.amazonaws.com/24/02/07/f6091fef-b9f9-4632-8eb0-d0e27de0123e_1636995577030.jpg",
        "alt": "1636995577030.jpg"
      },
      "location": {
        "notes": "Autocompleted using Google Maps API (id: ChIJkWK-FBFsEg0RSFb-HGIY8DQ)",
        "country": "España",
        "region": "Andalucía",
        "municipality": "Sevilla"
      }
    },
    "recommendations": [
      {
        "title": "ABC: Always Be Coding",
        "type": "reading",
        "URL": "https://medium.com/always-be-coding/d5f8051afce2",
        "authors": [
          {
            "name": "David",
            "surnames": "Byttow",
            "title": "Author"
          }
        ]
      },
      {
        "title": "Clean Code",
        "type": "reading",
        "URL": "https://www.amazon.es/Clean-Code-Handbook-Software-Craftsmanship-ebook/dp/B001GSTOAM/ref=tmm_kin_swatch_0?_encoding=UTF8&qid=&sr=",
        "authors": [
          {
            "name": "Robert C.",
            "surnames": "Martin",
            "title": "Author"
          }
        ]
      },
      {
        "title": "Coding Interview University",
        "type": "reading",
        "URL": "https://github.com/jwasham/coding-interview-university/tree/main",
        "authors": [
          {
            "name": "kiwib0y",
            "surnames": "and others",
            "title": "Author"
          }
        ]
      }
    ],
    "relevantLinks": [
      {
        "type": "linkedin",
        "URL": "https://www.linkedin.com/in/nacho-cerrato/"
      },
      {
        "type": "twitter",
        "URL": "https://twitter.com/NachoCerrato"
      }
    ]
  },
  "experience": {
    "jobs": [
      {
  "organization": {
    "name": "Eqtic",
    "image": {
      "link": "https://media-asgard.s3.eu-west-1.amazonaws.com/24/07/10/0f2f0cfd-417b-411a-8a4d-2a1dc09abe4a_logo.jpg",
      "alt": "logo.jpg"
    }
  },
  "roles": [
    {
      "name": "Full Stack Developer",
      "startDate": "2024-03-01",
      "challenges": [
        {
"description": "Currently working on multiple projects using various versions of .NET (primarily .NET 8), with Azure mainly used for project management through Azure DevOps. My primary focus is the modernization of legacy systems. I am heavily involved in a key project developing a new .NET 8 solution, replacing an outdated ASP.NET Web Forms application. The project was started from scratch, using Onion Architecture and Razor Pages to create a scalable and maintainable system, following Clean Architecture principles and SOLID design patterns.\n\n**Responsibilities**\n\n- Developed new modules within the project, ensuring a clear separation of concerns by isolating business logic in the Domain layer and using dependency injection to enhance testability and flexibility.\n- Applied the Specification Pattern to encapsulate business rules for querying data, improving code maintainability and reducing duplication.\n- Integrated Entity Framework Core using a Code-First approach, leveraging Fluent API for detailed configuration of entity relationships and database schema definitions.\n- Created and modified views and pages using HTML, CSS, JavaScript, and jQuery, working with ViewModels and integrating them with controllers via Axios to manage data flow and ensure proper front-end rendering."

        }
      ],
      "competences": [
        {
          "name": "C#",
          "type": "technology"
        },
        {
          "name": ".NET 8",
          "type": "technology"
        },
        {
          "name": "ASP.NET Core",
          "type": "technology"
        },
        {
          "name": "Razor Pages",
          "type": "technology"
        },
        {
          "name": "Entity Framework Core",
          "type": "technology"
        },
        {
          "name": "jQuery",
          "type": "technology"
        },
        {
          "name": "AutoMapper",
          "type": "technology"
        },
        {
          "name": "SQL Server",
          "type": "technology"
        },
        {
          "name": "HTML",
          "type": "technology"
        },
        {
          "name": "CSS",
          "type": "technology"
        },
        {
          "name": "JavaScript",
          "type": "technology"
        },
        {
          "name": "Axios",
          "type": "technology"
        },
        {
          "name": "Azure DevOps",
          "type": "technology"
        },
        {
          "name": "Git",
          "type": "technology"
        }
      ]
    }
  ]
}
,
      {
        "organization": {
          "name": "Deloitte",
          "image": {
            "link": "https://media-asgard.s3.eu-west-1.amazonaws.com/24/07/10/49c7be0c-c940-4bc1-b5a7-f63c9c699952_deloit.jpg",
            "alt": "deloit.jpg"
          }
        },
        "roles": [
          {
            "name": "Microsoft .NET & Azure Developer",
            "startDate": "2022-02-01",
            "finishDate": "2024-03-01",
            "challenges": [
              {
"description": "Developed and maintained web applications for Mercedes Benz in collaboration with Deloitte Germany. The primary focus of the project was the migration of an existing monolithic application to a microservices architecture, improving scalability, maintainability, and performance. This involved refactoring legacy systems and creating new APIs to ensure seamless communication between the new services.\n\n**Responsibilities:**\n\n- Developed and maintained REST APIs to enable efficient communication between different system components, facilitating the migration to a microservices architecture.\n- Conducted unit tests (xUnit) and integration tests to ensure code quality and functionality in critical areas of the system.\n- Actively contributed to bug fixing and the implementation of functional improvements to enhance system performance and reliability.\n- Refactored legacy code and new modules to improve code quality, enhance maintainability, and align with modern coding standards and best practices, including SOLID principles."
              }
            ],
            "competences": [
              {
                "name": "C#",
                "type": "technology"
              },
              {
                "name": ".NET 6",
                "type": "technology"
              },
              {
                "name": ".NET 4.7.2",
                "type": "technology"
              },
              {
                "name": "Microservices",
                "type": "technology"
              },
              {
                "name": "Azure Services (DevOps, Queue Storage, WebJobs, Blob Storage)",
                "type": "technology"
              },
              {
                "name": "SQL Server",
                "type": "technology"
              },
              {
                "name": "jUnit",
                "type": "technology"
              },
              {
                "name": "Entity Framework Core",
                "type": "technology"
              },
              {
                "name": "LinQ",
                "type": "technology"
              },
              {
                "name": "Git",
                "type": "technology"
              },
              {
                "name": "Agile",
                "type": "technology"
              }
            ]
          }
        ]
      },
      {
        "organization": {
          "name": "Cuonda Podcast"
        },
        "roles": [
          {
            "name": "Podcaster",
            "startDate": "2021-08-01",
            "finishDate": "2022-05-31",
            "challenges": [
              {
                "description": "Produced, wrote, recorded, and edited a daily podcast summarizing the latest news in the video game industry. Episodes were concise, providing listeners with updates in under 10 minutes."
              }
            ]
          }
        ]
      },
      {
        "organization": {
          "name": "Lúmina Energía"
        },
        "roles": [
          {
            "name": "Administrative Accountant",
            "startDate": "2021-01-01",
            "finishDate": "2021-08-31",
            "challenges": [
              {
                "description": "- Managed cash flow, income, and expense budgets.\n- Reconciliation and management of invoices and supplier payments."
              }
            ]
          }
        ]
      }
    ]
  },
  "knowledge": {
    "languages": [
      {
        "name": "EN",
        "fullName": "Inglés",
        "level": "Professional working proficiency"
      },
      {
        "name": "ES",
        "fullName": "Español",
        "level": "Native or bilingual proficiency"
      }
    ],
    "hardSkills": [
      {
        "skill": {
          "name": ".NET",
          "type": "technology"
        }
      },
      {
        "skill": {
          "name": ".NET Core",
          "type": "technology"
        }
      },
      {
        "skill": {
          "name": "API",
          "type": "technology"
        }
      },
      {
        "skill": {
          "name": "Azure",
          "type": "technology"
        }
      },
      {
        "skill": {
          "name": "C#",
          "type": "technology"
        }
      },
      {
        "skill": {
          "name": "Git",
          "type": "technology"
        }
      },
      {
        "skill": {
          "name": "SQL Server",
          "type": "technology"
        }
      }
    ],
    "studies": [
      {
        "studyType": "certification",
        "degreeAchieved": true,
        "name": "Azure Developer Associate",
        "startDate": "2023-03-01",
        "institution": {
          "name": "Microsoft",
          "URL": "https://www.credly.com/badges/44b2cb60-e5a5-443d-9237-0068c7707981"
        },
        "finishDate": "2025-03-01",
        "linkedCompetences": [
          {
            "name": "Azure",
            "type": "technology"
          }
        ]
      },
      {
        "studyType": "certification",
        "degreeAchieved": true,
        "name": "Power Platform App Maker Associate",
        "startDate": "2023-02-01",
        "institution": {
          "name": "Microsoft",
          "URL": "https://www.credly.com/badges/e7a778b5-0e88-44e2-b6d8-70a88144519f"
        },
        "finishDate": "2025-02-01",
        "linkedCompetences": [
          {
            "name": "Azure",
            "type": "technology"
          }
        ]
      },
      {
        "studyType": "officialDegree",
        "degreeAchieved": true,
        "name": "Web Application Development",
        "startDate": "2013-09-01",
        "institution": {
          "name": "IES Hermanos Machado"
        },
        "finishDate": "2015-07-01",
        "linkedCompetences": [
          {
            "name": "C",
            "type": "technology"
          },
          {
            "name": "CSS",
            "type": "technology"
          },
          {
            "name": "Java",
            "type": "technology"
          },
          {
            "name": "JavaScript",
            "type": "technology"
          },
          {
            "name": "SQL",
            "type": "technology"
          },
          {
            "name": "jQuery",
            "type": "technology"
          }
        ]
      }
    ]
  },
  "careerPreferences": {
    "contact": {
      "publicProfiles": [
        {
          "URL": "https://www.linkedin.com/in/nacho-cerrato/",
          "type": "linkedin"
        },
        {
          "URL": "https://twitter.com/NachoCerrato",
          "type": "twitter"
        }
      ],
      "contactMails": [
        "igncerrui@gmail.com"
      ]
    },
    "preferences": {
      "preferredCompetences": [
        {
          "name": ".NET",
          "type": "technology"
        },
        {
          "name": "Azure",
          "type": "technology"
        },
        {
          "name": "C#",
          "type": "technology"
        },
        {
          "name": "CSS",
          "type": "technology"
        },
        {
          "name": "Entity",
          "type": "technology"
        },
        {
          "name": "HTML",
          "type": "technology"
        },
        {
          "name": "JavaScript",
          "type": "technology"
        },
        {
          "name": "LinQ",
          "type": "technology"
        },
        {
          "name": "Python",
          "type": "technology"
        },
        {
          "name": "React",
          "type": "technology"
        },
        {
          "name": "SQLServer",
          "type": "technology"
        },
        {
          "name": "Swift",
          "type": "technology"
        }
      ],
      "discardedCompetences": [
        {
          "name": "PHP",
          "type": "technology"
        },
        {
          "name": "PL/SQL",
          "type": "technology"
        }
      ],
      "preferredRoles": [
        "Backend Developer",
        "Full-stack Developer"
      ]
    },
    "status": "searchingActively"
  },
  "manfredSpecificData": {
    "mainStackTechs": [
      {
        "name": ".NET Core",
        "type": "technology"
      },
      {
        "name": "API",
        "type": "technology"
      },
      {
        "name": "Azure",
        "type": "technology"
      },
      {
        "name": "C#",
        "type": "technology"
      },
      {
        "name": "SQL Server",
        "type": "technology"
      }
    ],
    "desiredJobDescription": "My dream job is one that allows me to grow as a developer, work with interesting projects, and apply best practices in a collaborative and team-oriented environment. I seek a role where continuous learning and quality are prioritized.",
    "goodPractices": "I have consistently applied good practices throughout my career, including Clean Architecture, SOLID principles, and CI/CD methodologies. I am committed to writing clean and maintainable code while continuously improving my skills by studying resources like Clean Code by Uncle Bob.",
    "bookmarks": [
      {
        "name": "ABC: Always Be Coding"
      },
      {
        "name": "Clean Code"
      },
      {
        "name": "Coding Interview University"
      }
    ]
  }
}
